sample/__init__.py
linuxstream-1.1.0.dist-info/METADATA
linuxstream-1.1.0.dist-info/WHEEL
linuxstream-1.1.0.dist-info/entry_points.txt
linuxstream-1.1.0.dist-info/top_level.txt
linuxstream-1.1.0.dist-info/RECORD
