Metadata-Version: 2.1
Name: linuxstream
Version: 1.1.0
Summary: A sample Python project
Home-page: https://github.com/pypa/linuxstream
Author: dushuangshuang
Author-email: shuang2du@163.com
License: UNKNOWN
Project-URL: Bug Reports, https://github.com/pypa/dsssample/issues
Project-URL: Funding, https://donate.pypi.org
Project-URL: Say Thanks!, http://saythanks.io/to/example
Project-URL: Source, https://github.com/pypa/dsssample/
Keywords: sample,setuptools,development
Platform: UNKNOWN
Classifier: Development Status :: 3 - Alpha
Classifier: Intended Audience :: Developers
Classifier: Topic :: Software Development :: Build Tools
Classifier: License :: OSI Approved :: MIT License
Classifier: Programming Language :: Python :: 3
Classifier: Programming Language :: Python :: 3.7
Classifier: Programming Language :: Python :: 3.8
Classifier: Programming Language :: Python :: 3.9
Classifier: Programming Language :: Python :: 3 :: Only
Requires-Python: >=3.7, <4
Requires-Dist: numpy
Requires-Dist: openpyxl
Requires-Dist: chardet
Requires-Dist: requests
Requires-Dist: certifi
Provides-Extra: dev
Requires-Dist: check-manifest ; extra == 'dev'
Provides-Extra: test
Requires-Dist: coverage ; extra == 'test'
